[{"DocumentKeywordVectors":[{"TotalDocumentLength":866,"PageCount":1,"FirstPageVector":{"VectorId":"sample.accounts.invoices_1.FirstPage","DocumentCount":1,"TermsWithScores":[{"Score":0.97,"Term":"invoice","LastUpdated":"2026-03-10T15:25:08.3255764+05:30"},{"Score":0.75,"Term":"demo","LastUpdated":"2026-03-10T15:25:08.3255708+05:30"},{"Score":0.75,"Term":"sliced","LastUpdated":"2026-03-10T15:25:08.325575+05:30"},{"Score":0.74,"Term":"invoices","LastUpdated":"2026-03-10T15:25:08.3255891+05:30"},{"Score":0.71,"Term":"slicedinvoices","LastUpdated":"2026-03-10T15:25:08.3255685+05:30"},{"Score":0.71,"Term":"total","LastUpdated":"2026-03-10T15:25:08.325573+05:30"},{"Score":0.67,"Term":"january","LastUpdated":"2026-03-10T15:25:08.3255783+05:30"},{"Score":0.59,"Term":"suite","LastUpdated":"2026-03-10T15:25:08.325583+05:30"},{"Score":0.53,"Term":"street","LastUpdated":"2026-03-10T15:25:08.3255858+05:30"},{"Score":0.49,"Term":"city","LastUpdated":"2026-03-10T15:25:08.3255897+05:30"},{"Score":0.4,"Term":"business","LastUpdated":"2026-03-10T15:25:08.3255877+05:30"},{"Score":0.38,"Term":"melbourne","LastUpdated":"2026-03-10T15:25:08.3255692+05:30"},{"Score":0.37,"Term":"vic","LastUpdated":"2026-03-10T15:25:08.3255851+05:30"},{"Score":0.34,"Term":"service","LastUpdated":"2026-03-10T15:25:08.3255903+05:30"},{"Score":0.33,"Term":"design","LastUpdated":"2026-03-10T15:25:08.3255792+05:30"},{"Score":0.32,"Term":"sample","LastUpdated":"2026-03-10T15:25:08.3255699+05:30"},{"Score":0.31,"Term":"description","LastUpdated":"2026-03-10T15:25:08.3255715+05:30"},{"Score":0.3,"Term":"payment","LastUpdated":"2026-03-10T15:25:08.3255757+05:30"},{"Score":0.28,"Term":"tax","LastUpdated":"2026-03-10T15:25:08.3255723+05:30"},{"Score":0.25,"Term":"bank","LastUpdated":"2026-03-10T15:25:08.3255771+05:30"},{"Score":0.25,"Term":"acc","LastUpdated":"2026-03-10T15:25:08.3255777+05:30"},{"Score":0.25,"Term":"anz","LastUpdated":"2026-03-10T15:25:08.3255798+05:30"},{"Score":0.24,"Term":"bsb","LastUpdated":"2026-03-10T15:25:08.3255864+05:30"},{"Score":0.21,"Term":"adjust","LastUpdated":"2026-03-10T15:25:08.3255845+05:30"},{"Score":0.16,"Term":"days","LastUpdated":"2026-03-10T15:25:08.3255871+05:30"},{"Score":0.14,"Term":"late","LastUpdated":"2026-03-10T15:25:08.3255744+05:30"},{"Score":0.13,"Term":"subject","LastUpdated":"2026-03-10T15:25:08.3255884+05:30"},{"Score":0.12,"Term":"fees","LastUpdated":"2026-03-10T15:25:08.3255678+05:30"},{"Score":0.11,"Term":"month","LastUpdated":"2026-03-10T15:25:08.3255738+05:30"},{"Score":0.1,"Term":"choosing","LastUpdated":"2026-03-10T15:25:08.3255838+05:30"},{"Score":0.04,"Term":"paid","LastUpdated":"2026-03-10T15:25:08.3255657+05:30"}]},"RestOfPagesVector":{"VectorId":"sample.accounts.invoices_1.RestOfPages","DocumentCount":1,"TermsWithScores":[]},"ParentVectorId":"sample.accounts.invoices","VectorId":"sample.accounts.invoices_1","DocumentCount":1,"TermsWithScores":[{"Score":0.97,"Term":"invoice","LastUpdated":"2026-03-10T15:25:08.3266707+05:30"},{"Score":0.75,"Term":"demo","LastUpdated":"2026-03-10T15:25:08.3266616+05:30"},{"Score":0.75,"Term":"sliced","LastUpdated":"2026-03-10T15:25:08.3266685+05:30"},{"Score":0.74,"Term":"invoices","LastUpdated":"2026-03-10T15:25:08.3266875+05:30"},{"Score":0.71,"Term":"slicedinvoices","LastUpdated":"2026-03-10T15:25:08.326658+05:30"},{"Score":0.71,"Term":"total","LastUpdated":"2026-03-10T15:25:08.3266652+05:30"},{"Score":0.67,"Term":"january","LastUpdated":"2026-03-10T15:25:08.326674+05:30"},{"Score":0.59,"Term":"suite","LastUpdated":"2026-03-10T15:25:08.3266783+05:30"},{"Score":0.53,"Term":"street","LastUpdated":"2026-03-10T15:25:08.3266823+05:30"},{"Score":0.49,"Term":"city","LastUpdated":"2026-03-10T15:25:08.3266883+05:30"},{"Score":0.4,"Term":"business","LastUpdated":"2026-03-10T15:25:08.3266856+05:30"},{"Score":0.38,"Term":"melbourne","LastUpdated":"2026-03-10T15:25:08.3266593+05:30"},{"Score":0.37,"Term":"vic","LastUpdated":"2026-03-10T15:25:08.3266814+05:30"},{"Score":0.34,"Term":"service","LastUpdated":"2026-03-10T15:25:08.3266893+05:30"},{"Score":0.33,"Term":"design","LastUpdated":"2026-03-10T15:25:08.3266755+05:30"},{"Score":0.32,"Term":"sample","LastUpdated":"2026-03-10T15:25:08.3266602+05:30"},{"Score":0.31,"Term":"description","LastUpdated":"2026-03-10T15:25:08.3266627+05:30"},{"Score":0.3,"Term":"payment","LastUpdated":"2026-03-10T15:25:08.3266696+05:30"},{"Score":0.28,"Term":"tax","LastUpdated":"2026-03-10T15:25:08.3266639+05:30"},{"Score":0.25,"Term":"bank","LastUpdated":"2026-03-10T15:25:08.3266717+05:30"},{"Score":0.25,"Term":"acc","LastUpdated":"2026-03-10T15:25:08.3266729+05:30"},{"Score":0.25,"Term":"anz","LastUpdated":"2026-03-10T15:25:08.3266772+05:30"},{"Score":0.24,"Term":"bsb","LastUpdated":"2026-03-10T15:25:08.3266832+05:30"},{"Score":0.21,"Term":"adjust","LastUpdated":"2026-03-10T15:25:08.3266804+05:30"},{"Score":0.16,"Term":"days","LastUpdated":"2026-03-10T15:25:08.3266841+05:30"},{"Score":0.14,"Term":"late","LastUpdated":"2026-03-10T15:25:08.3266674+05:30"},{"Score":0.13,"Term":"subject","LastUpdated":"2026-03-10T15:25:08.3266865+05:30"},{"Score":0.12,"Term":"fees","LastUpdated":"2026-03-10T15:25:08.3266565+05:30"},{"Score":0.11,"Term":"month","LastUpdated":"2026-03-10T15:25:08.3266665+05:30"},{"Score":0.1,"Term":"choosing","LastUpdated":"2026-03-10T15:25:08.3266794+05:30"},{"Score":0.04,"Term":"paid","LastUpdated":"2026-03-10T15:25:08.3266522+05:30"}]}],"TotalDocumentLength":866,"PageCount":1,"FirstPageVector":{"VectorId":"sample.accounts.invoices.FirstPage","DocumentCount":1,"TermsWithScores":[{"Score":0.97,"Term":"invoice","LastUpdated":"2026-03-10T15:25:08.3074159+05:30"},{"Score":0.75,"Term":"demo","LastUpdated":"2026-03-10T15:25:08.3074037+05:30"},{"Score":0.75,"Term":"sliced","LastUpdated":"2026-03-10T15:25:08.3074141+05:30"},{"Score":0.74,"Term":"invoices","LastUpdated":"2026-03-10T15:25:08.3074279+05:30"},{"Score":0.71,"Term":"slicedinvoices","LastUpdated":"2026-03-10T15:25:08.3073992+05:30"},{"Score":0.71,"Term":"total","LastUpdated":"2026-03-10T15:25:08.3074067+05:30"},{"Score":0.67,"Term":"january","LastUpdated":"2026-03-10T15:25:08.3074181+05:30"},{"Score":0.59,"Term":"suite","LastUpdated":"2026-03-10T15:25:08.3074206+05:30"},{"Score":0.53,"Term":"street","LastUpdated":"2026-03-10T15:25:08.3074234+05:30"},{"Score":0.49,"Term":"city","LastUpdated":"2026-03-10T15:25:08.3074285+05:30"},{"Score":0.4,"Term":"business","LastUpdated":"2026-03-10T15:25:08.307426+05:30"},{"Score":0.38,"Term":"melbourne","LastUpdated":"2026-03-10T15:25:08.3074006+05:30"},{"Score":0.37,"Term":"vic","LastUpdated":"2026-03-10T15:25:08.3074228+05:30"},{"Score":0.34,"Term":"service","LastUpdated":"2026-03-10T15:25:08.3074291+05:30"},{"Score":0.33,"Term":"design","LastUpdated":"2026-03-10T15:25:08.3074191+05:30"},{"Score":0.32,"Term":"sample","LastUpdated":"2026-03-10T15:25:08.3074017+05:30"},{"Score":0.31,"Term":"description","LastUpdated":"2026-03-10T15:25:08.3074048+05:30"},{"Score":0.3,"Term":"payment","LastUpdated":"2026-03-10T15:25:08.3074148+05:30"},{"Score":0.28,"Term":"tax","LastUpdated":"2026-03-10T15:25:08.3074056+05:30"},{"Score":0.25,"Term":"bank","LastUpdated":"2026-03-10T15:25:08.3074167+05:30"},{"Score":0.25,"Term":"acc","LastUpdated":"2026-03-10T15:25:08.3074174+05:30"},{"Score":0.25,"Term":"anz","LastUpdated":"2026-03-10T15:25:08.30742+05:30"},{"Score":0.24,"Term":"bsb","LastUpdated":"2026-03-10T15:25:08.3074241+05:30"},{"Score":0.21,"Term":"adjust","LastUpdated":"2026-03-10T15:25:08.3074222+05:30"},{"Score":0.16,"Term":"days","LastUpdated":"2026-03-10T15:25:08.3074251+05:30"},{"Score":0.14,"Term":"late","LastUpdated":"2026-03-10T15:25:08.3074133+05:30"},{"Score":0.13,"Term":"subject","LastUpdated":"2026-03-10T15:25:08.3074267+05:30"},{"Score":0.12,"Term":"fees","LastUpdated":"2026-03-10T15:25:08.3073971+05:30"},{"Score":0.11,"Term":"month","LastUpdated":"2026-03-10T15:25:08.3074122+05:30"},{"Score":0.1,"Term":"choosing","LastUpdated":"2026-03-10T15:25:08.3074214+05:30"},{"Score":0.04,"Term":"paid","LastUpdated":"2026-03-10T15:25:08.3071492+05:30"}]},"RestOfPagesVector":{"VectorId":"sample.accounts.invoices.RestOfPages","DocumentCount":1,"TermsWithScores":[]},"ParentVectorId":null,"VectorId":"sample.accounts.invoices","DocumentCount":1,"TermsWithScores":[{"Score":0.97,"Term":"invoice","LastUpdated":"2026-03-10T15:25:08.3249537+05:30"},{"Score":0.75,"Term":"demo","LastUpdated":"2026-03-10T15:25:08.3249488+05:30"},{"Score":0.75,"Term":"sliced","LastUpdated":"2026-03-10T15:25:08.3249526+05:30"},{"Score":0.74,"Term":"invoices","LastUpdated":"2026-03-10T15:25:08.3249643+05:30"},{"Score":0.71,"Term":"slicedinvoices","LastUpdated":"2026-03-10T15:25:08.3249466+05:30"},{"Score":0.71,"Term":"total","LastUpdated":"2026-03-10T15:25:08.3249508+05:30"},{"Score":0.67,"Term":"january","LastUpdated":"2026-03-10T15:25:08.3249556+05:30"},{"Score":0.59,"Term":"suite","LastUpdated":"2026-03-10T15:25:08.3249575+05:30"},{"Score":0.53,"Term":"street","LastUpdated":"2026-03-10T15:25:08.3249599+05:30"},{"Score":0.49,"Term":"city","LastUpdated":"2026-03-10T15:25:08.3249649+05:30"},{"Score":0.4,"Term":"business","LastUpdated":"2026-03-10T15:25:08.3249631+05:30"},{"Score":0.38,"Term":"melbourne","LastUpdated":"2026-03-10T15:25:08.3249474+05:30"},{"Score":0.37,"Term":"vic","LastUpdated":"2026-03-10T15:25:08.3249593+05:30"},{"Score":0.34,"Term":"service","LastUpdated":"2026-03-10T15:25:08.3249654+05:30"},{"Score":0.33,"Term":"design","LastUpdated":"2026-03-10T15:25:08.3249563+05:30"},{"Score":0.32,"Term":"sample","LastUpdated":"2026-03-10T15:25:08.324948+05:30"},{"Score":0.31,"Term":"description","LastUpdated":"2026-03-10T15:25:08.3249495+05:30"},{"Score":0.3,"Term":"payment","LastUpdated":"2026-03-10T15:25:08.3249532+05:30"},{"Score":0.28,"Term":"tax","LastUpdated":"2026-03-10T15:25:08.3249502+05:30"},{"Score":0.25,"Term":"bank","LastUpdated":"2026-03-10T15:25:08.3249543+05:30"},{"Score":0.25,"Term":"acc","LastUpdated":"2026-03-10T15:25:08.324955+05:30"},{"Score":0.25,"Term":"anz","LastUpdated":"2026-03-10T15:25:08.3249569+05:30"},{"Score":0.24,"Term":"bsb","LastUpdated":"2026-03-10T15:25:08.3249618+05:30"},{"Score":0.21,"Term":"adjust","LastUpdated":"2026-03-10T15:25:08.3249587+05:30"},{"Score":0.16,"Term":"days","LastUpdated":"2026-03-10T15:25:08.3249624+05:30"},{"Score":0.14,"Term":"late","LastUpdated":"2026-03-10T15:25:08.324952+05:30"},{"Score":0.13,"Term":"subject","LastUpdated":"2026-03-10T15:25:08.3249637+05:30"},{"Score":0.12,"Term":"fees","LastUpdated":"2026-03-10T15:25:08.3249458+05:30"},{"Score":0.11,"Term":"month","LastUpdated":"2026-03-10T15:25:08.3249514+05:30"},{"Score":0.1,"Term":"choosing","LastUpdated":"2026-03-10T15:25:08.3249582+05:30"},{"Score":0.04,"Term":"paid","LastUpdated":"2026-03-10T15:25:08.3249423+05:30"}]}]
